MANIFEST.in
README.md
requirements.txt
setup.cfg
setup.py
talentiumkg/__init__.py
talentiumkg/talentiumkg.py
talentiumkg.egg-info/PKG-INFO
talentiumkg.egg-info/SOURCES.txt
talentiumkg.egg-info/dependency_links.txt
talentiumkg.egg-info/requires.txt
talentiumkg.egg-info/top_level.txt
talentiumkg/data/__init__.py
talentiumkg/data/common_relations.csv
talentiumkg/data/relations.csv
talentiumkg/data/skills.csv
talentiumkg/data/titles.csv