Metadata-Version: 2.1
Name: talentiumkg
Version: 0.0.7
Summary: talentium kg wrapper
License: MIT
